{
  "title": "Love Revolution",
  "description": "",
  "artist": "",
  "author": "",
  "cover": "https://meo.comick.pictures/e2G5X-m.jpg",
  "chapters": {
    "89": {
      "title": "89",
      "volume": "",
      "last_updated": "1751371319",
      "groups": {
        "": [
          "https://files.catbox.moe/n1mmx5.png",
          "https://files.catbox.moe/lkopa9.png",
          "https://files.catbox.moe/5p3myz.png",
          "https://files.catbox.moe/bollue.png",
          "https://files.catbox.moe/xs8cud.png",
          "https://files.catbox.moe/zc4awx.png",
          "https://files.catbox.moe/ymvir0.png"
        ]
      }
    },
    "90": {
      "title": "90",
      "volume": "",
      "last_updated": "1751371396",
      "groups": {
        "": [
          "https://files.catbox.moe/5woo4s.png",
          "https://files.catbox.moe/cgumsb.png",
          "https://files.catbox.moe/lsk2wx.png",
          "https://files.catbox.moe/32ztic.png",
          "https://files.catbox.moe/snot90.png",
          "https://files.catbox.moe/vua1wl.png",
          "https://files.catbox.moe/alwgy5.png"
        ]
      }
    }
  }
}